shared_event/__init__.py
shared_event/event.py
shared_event-0.1.0.dist-info/METADATA
shared_event-0.1.0.dist-info/WHEEL
shared_event-0.1.0.dist-info/top_level.txt
shared_event-0.1.0.dist-info/RECORD
