Metadata-Version: 2.4
Name: shared_event
Version: 0.1.0
Summary: A shared-memory based multiprocessing event using atomics
Author-email: Raymond Chastain <RaymondLC92@protonmail.com>
License: MIT
Keywords: python,package
Classifier: Development Status :: 4 - Beta
Classifier: Intended Audience :: Developers
Classifier: License :: OSI Approved :: MIT License
Classifier: Programming Language :: Python :: 3.13
Requires-Python: >=3.13.7
